Metadata-Version: 1.0
Name: linkedlist
Version: 1.0.0
Summary: General purpose linked list
Home-page: https://github.com/teroqim/linkedlist
Author: Peter Andersson
Author-email: teroqim@gmail.com
License: UNKNOWN
Platform: UNKNOWN
